LICENSE
README.md
setup.py
atlascli/__init__.py
atlascli/__main__.py
atlascli/atlasapi.py
atlascli/atlascluster.py
atlascli/atlascommand.py
atlascli/atlaserrors.py
atlascli/atlaskey.py
atlascli/atlasorganization.py
atlascli/atlasproject.py
atlascli/atlasresource.py
atlascli/command.py
atlascli/createcommand.py
atlascli/errors.py
atlascli/main.py
atlascli/opcapi.py
atlascli/outputformat.py
atlascli/requestgroup.py
atlascli/version.py
atlascli.egg-info/PKG-INFO
atlascli.egg-info/SOURCES.txt
atlascli.egg-info/dependency_links.txt
atlascli.egg-info/entry_points.txt
atlascli.egg-info/requires.txt
atlascli.egg-info/top_level.txt
test/__init__.py
test/pauseresume.py
test/test_api.py
test/test_atlas_apimixin.py
test/test_atlasapi.py
test/test_atlascluster.py
test/test_atlaskey.py
test/test_atlasproject.py
test/test_organization.py