Metadata-Version: 2.1
Name: atlascli
Version: 0.2.8
Summary: Simple cli to pause and resume Atlas Clusters
Home-page: https://github.com/jdrumgoole/atlascli
Author: Joe Drumgoole
Author-email: joe@joedrumgoole.com
License: Apache 2.0
Platform: UNKNOWN
Classifier: License :: OSI Approved :: Apache Software License
Classifier: Programming Language :: Python
Classifier: Programming Language :: Python :: 3
Classifier: Programming Language :: Python :: 3.6
Classifier: Programming Language :: Python :: Implementation :: CPython
Classifier: Programming Language :: Python :: Implementation :: PyPy
Requires-Python: >=3.6.0
